lice2/__init__.py
lice2/config.py
lice2/constants.py
lice2/core.py
lice2/helpers.py
lice2/api/__init__.py
lice2/api/api.py
lice2/api/exceptions.py
lice2/templates/__init__.py
lice2/templates/template-afl3.txt
lice2/templates/template-agpl3-header.txt
lice2/templates/template-agpl3.txt
lice2/templates/template-al2.txt
lice2/templates/template-apache-header.txt
lice2/templates/template-apache.txt
lice2/templates/template-bsd2.txt
lice2/templates/template-bsd3.txt
lice2/templates/template-cc0-header.txt
lice2/templates/template-cc0.txt
lice2/templates/template-cc_by-header.txt
lice2/templates/template-cc_by.txt
lice2/templates/template-cc_by_nc-header.txt
lice2/templates/template-cc_by_nc.txt
lice2/templates/template-cc_by_nc_nd-header.txt
lice2/templates/template-cc_by_nc_nd.txt
lice2/templates/template-cc_by_nc_sa-header.txt
lice2/templates/template-cc_by_nc_sa.txt
lice2/templates/template-cc_by_nd-header.txt
lice2/templates/template-cc_by_nd.txt
lice2/templates/template-cc_by_sa-header.txt
lice2/templates/template-cc_by_sa.txt
lice2/templates/template-cddl.txt
lice2/templates/template-edl.txt
lice2/templates/template-epl.txt
lice2/templates/template-eupl.txt
lice2/templates/template-gpl2-header.txt
lice2/templates/template-gpl2.txt
lice2/templates/template-gpl3-header.txt
lice2/templates/template-gpl3.txt
lice2/templates/template-isc.txt
lice2/templates/template-lgpl.txt
lice2/templates/template-mit.txt
lice2/templates/template-mpl-header.txt
lice2/templates/template-mpl.txt
lice2/templates/template-ofl.txt
lice2/templates/template-unlicense.txt
lice2/templates/template-wtfpl-header.txt
lice2/templates/template-wtfpl.txt
lice2/templates/template-zlib.txt
lice2/tests/__init__.py
lice2/tests/conftest.py
lice2/tests/test_api.py
lice2/tests/test_cli.py
lice2/tests/test_lice.py
lice2-0.13.0.dist-info/METADATA
lice2-0.13.0.dist-info/WHEEL
lice2-0.13.0.dist-info/entry_points.txt
lice2-0.13.0.dist-info/licenses/LICENSE
lice2-0.13.0.dist-info/RECORD
