Metadata-Version: 2.3
Name: lice2
Version: 0.13.0
Summary: Generate license files for your projects
Project-URL: repository, https://github.com/seapagan/lice2
Project-URL: homepage, https://seapagan.github.io/lice2/
Project-URL: Pull Requests, https://github.com/seapagan/lice2/pulls
Project-URL: Bug Tracker, https://github.com/seapagan/lice2/issues
Project-URL: Changelog, https://github.com/seapagan/lice2/blob/main/CHANGELOG.md
Author-email: Grant Ramsay <grant@gnramsay.com>
License: BSD-3-Clause
Classifier: Development Status :: 4 - Beta
Classifier: Intended Audience :: Developers
Classifier: License :: OSI Approved :: BSD License
Classifier: Operating System :: OS Independent
Classifier: Programming Language :: Python :: 3
Classifier: Programming Language :: Python :: 3.9
Classifier: Programming Language :: Python :: 3.10
Classifier: Programming Language :: Python :: 3.11
Classifier: Programming Language :: Python :: 3.12
Requires-Python: >=3.9
Requires-Dist: pyperclip>=1.9.0
Requires-Dist: rich>=13.8.0
Requires-Dist: simple-toml-settings>=0.8.0
Requires-Dist: single-source>=0.4.0
Requires-Dist: typer>=0.12.5
